aliyunsdkcbn/__init__.py
aliyunsdkcbn/endpoint.py
aliyunsdkcbn/request/__init__.py
aliyunsdkcbn/request/v20170912/ActiveFlowLogRequest.py
aliyunsdkcbn/request/v20170912/AddTrafficMatchRuleToTrafficMarkingPolicyRequest.py
aliyunsdkcbn/request/v20170912/AddTraficMatchRuleToTrafficMarkingPolicyRequest.py
aliyunsdkcbn/request/v20170912/AssociateCenBandwidthPackageRequest.py
aliyunsdkcbn/request/v20170912/AssociateTransitRouterAttachmentWithRouteTableRequest.py
aliyunsdkcbn/request/v20170912/AssociateTransitRouterMulticastDomainRequest.py
aliyunsdkcbn/request/v20170912/AttachCenChildInstanceRequest.py
aliyunsdkcbn/request/v20170912/CheckTransitRouterServiceRequest.py
aliyunsdkcbn/request/v20170912/CreateCenBandwidthPackageRequest.py
aliyunsdkcbn/request/v20170912/CreateCenChildInstanceRouteEntryToAttachmentRequest.py
aliyunsdkcbn/request/v20170912/CreateCenChildInstanceRouteEntryToCenRequest.py
aliyunsdkcbn/request/v20170912/CreateCenInterRegionTrafficQosPolicyRequest.py
aliyunsdkcbn/request/v20170912/CreateCenInterRegionTrafficQosQueueRequest.py
aliyunsdkcbn/request/v20170912/CreateCenRequest.py
aliyunsdkcbn/request/v20170912/CreateCenRouteMapRequest.py
aliyunsdkcbn/request/v20170912/CreateFlowlogRequest.py
aliyunsdkcbn/request/v20170912/CreateTrafficMarkingPolicyRequest.py
aliyunsdkcbn/request/v20170912/CreateTransitRouteTableAggregationRequest.py
aliyunsdkcbn/request/v20170912/CreateTransitRouterCidrRequest.py
aliyunsdkcbn/request/v20170912/CreateTransitRouterEcrAttachmentRequest.py
aliyunsdkcbn/request/v20170912/CreateTransitRouterMulticastDomainRequest.py
aliyunsdkcbn/request/v20170912/CreateTransitRouterPeerAttachmentRequest.py
aliyunsdkcbn/request/v20170912/CreateTransitRouterPrefixListAssociationRequest.py
aliyunsdkcbn/request/v20170912/CreateTransitRouterRequest.py
aliyunsdkcbn/request/v20170912/CreateTransitRouterRouteEntryRequest.py
aliyunsdkcbn/request/v20170912/CreateTransitRouterRouteTableRequest.py
aliyun_python_sdk_cbn-1.0.41.dist-info/LICENSE
aliyun_python_sdk_cbn-1.0.41.dist-info/METADATA
aliyun_python_sdk_cbn-1.0.41.dist-info/WHEEL
aliyun_python_sdk_cbn-1.0.41.dist-info/top_level.txt
aliyun_python_sdk_cbn-1.0.41.dist-info/RECORD
